garpundatahub/__init__.py
garpundatahub/client.py
garpundatahub/datahub.py
garpundatahub/info.py
garpundatahub-0.0.3.dist-info/LICENSE
garpundatahub-0.0.3.dist-info/METADATA
garpundatahub-0.0.3.dist-info/WHEEL
garpundatahub-0.0.3.dist-info/top_level.txt
garpundatahub-0.0.3.dist-info/RECORD
